README.txt
setup.cfg
setup.py
collective/__init__.py
collective.inplacetopicview.egg-info/PKG-INFO
collective.inplacetopicview.egg-info/SOURCES.txt
collective.inplacetopicview.egg-info/dependency_links.txt
collective.inplacetopicview.egg-info/entry_points.txt
collective.inplacetopicview.egg-info/namespace_packages.txt
collective.inplacetopicview.egg-info/not-zip-safe
collective.inplacetopicview.egg-info/paster_plugins.txt
collective.inplacetopicview.egg-info/requires.txt
collective.inplacetopicview.egg-info/top_level.txt
collective/inplacetopicview/__init__.py
collective/inplacetopicview/configure.zcml
collective/inplacetopicview/profiles.zcml
collective/inplacetopicview/browser/__init__.py
collective/inplacetopicview/browser/acquisition.pt
collective/inplacetopicview/browser/acquisition.py
collective/inplacetopicview/browser/configure.zcml
collective/inplacetopicview/browser/interfaces.py
collective/inplacetopicview/browser/twin.pt
collective/inplacetopicview/browser/twin.py
collective/inplacetopicview/profiles/default/metadata.xml
collective/inplacetopicview/profiles/default/types.xml
collective/inplacetopicview/profiles/default/types/Topic.xml
collective/inplacetopicview/tests/__init__.py
collective/inplacetopicview/tests/base.py
collective/inplacetopicview/tests/functional.txt
collective/inplacetopicview/tests/test_acquisition.py
collective/inplacetopicview/tests/test_functional_doctest.py
collective/inplacetopicview/tests/test_setup.py
collective/inplacetopicview/tests/test_twin.py
docs/HISTORY.txt
docs/INSTALL.txt
docs/LICENSE.GPL
docs/LICENSE.txt