Metadata-Version: 1.0
Name: collective.inplacetopicview
Version: 1.0
Summary: Lets view the content of an item listed by a topic within the topic context
Home-page: https://svn.plone.org/svn/collective/collective.inplacetopicview
Author: JeanMichel FRANCOIS aka toutpt
Author-email: jeanmichel.francois@makina-corpus.com
License: GPL
Keywords: plone collective
Platform: UNKNOWN
Classifier: Framework :: Plone
Classifier: Programming Language :: Python
